plonetheme.booster-1.0.6-py2.7-nspkg.pth
plonetheme/booster/__init__.py
plonetheme/booster/configure.zcml
plonetheme/booster/interfaces.py
plonetheme/booster/setuphandlers.py
plonetheme/booster/testing.py
plonetheme/booster/browser/__init__.py
plonetheme/booster/browser/configure.zcml
plonetheme/booster/browser/overrides/.gitkeep
plonetheme/booster/browser/static/.gitkeep
plonetheme/booster/locales/plonetheme.booster.pot
plonetheme/booster/locales/update.sh
plonetheme/booster/profiles/default/browserlayer.xml
plonetheme/booster/profiles/default/metadata.xml
plonetheme/booster/profiles/default/plonethemebooster_default.txt
plonetheme/booster/profiles/default/theme.xml
plonetheme/booster/profiles/uninstall/browserlayer.xml
plonetheme/booster/profiles/uninstall/plonethemebooster_uninstall.txt
plonetheme/booster/profiles/uninstall/theme.xml
plonetheme/booster/tests/__init__.py
plonetheme/booster/tests/test_robot.py
plonetheme/booster/tests/test_setup.py
plonetheme/booster/tests/robot/test_example.robot
plonetheme/booster/theme/README.txt
plonetheme/booster/theme/index.html
plonetheme/booster/theme/manifest.cfg
plonetheme/booster/theme/preview.png
plonetheme/booster/theme/rules.xml
plonetheme/booster/theme/fonts/.DS_Store
plonetheme/booster/theme/fonts/bootstrap/glyphicons-halflings-regular.eot
plonetheme/booster/theme/fonts/bootstrap/glyphicons-halflings-regular.svg
plonetheme/booster/theme/fonts/bootstrap/glyphicons-halflings-regular.ttf
plonetheme/booster/theme/fonts/bootstrap/glyphicons-halflings-regular.woff
plonetheme/booster/theme/fonts/bootstrap/glyphicons-halflings-regular.woff2
plonetheme/booster/theme/fonts/bootstrap/index.html
plonetheme/booster/theme/fonts/icomoon/.DS_Store
plonetheme/booster/theme/fonts/icomoon/icomoon.eot
plonetheme/booster/theme/fonts/icomoon/icomoon.svg
plonetheme/booster/theme/fonts/icomoon/icomoon.ttf
plonetheme/booster/theme/fonts/icomoon/icomoon.woff
plonetheme.booster-1.0.6.dist-info/DESCRIPTION.rst
plonetheme.booster-1.0.6.dist-info/METADATA
plonetheme.booster-1.0.6.dist-info/RECORD
plonetheme.booster-1.0.6.dist-info/WHEEL
plonetheme.booster-1.0.6.dist-info/entry_points.txt
plonetheme.booster-1.0.6.dist-info/metadata.json
plonetheme.booster-1.0.6.dist-info/namespace_packages.txt
plonetheme.booster-1.0.6.dist-info/top_level.txt
